split_gpx/__init__.py
split_gpx/__main__.py
split_gpx/py.typed
split_gpx/split_gpx.py
split_gpx-0.2.1.dist-info/LICENSE.txt
split_gpx-0.2.1.dist-info/METADATA
split_gpx-0.2.1.dist-info/WHEEL
split_gpx-0.2.1.dist-info/entry_points.txt
split_gpx-0.2.1.dist-info/top_level.txt
split_gpx-0.2.1.dist-info/RECORD
