Metadata-Version: 2.1
Name: split-gpx
Version: 0.2.1
Summary: Split a GPX tracks into multiple parts
Author: FriedrichFröbel
License: MIT
Project-URL: Homepage, https://github.com/FriedrichFroebel/split_gpx
Project-URL: Repository, https://github.com/FriedrichFroebel/split_gpx
Project-URL: Issues, https://github.com/FriedrichFroebel/split_gpx/issues
Project-URL: Changelog, https://github.com/FriedrichFroebel/split_gpx/blob/main/CHANGELOG.md
Keywords: gps,gpx,track
Classifier: Development Status :: 4 - Beta
Classifier: Environment :: Console
Classifier: Intended Audience :: Developers
Classifier: License :: OSI Approved :: MIT License
Classifier: Programming Language :: Python :: 3
Classifier: Programming Language :: Python :: 3 :: Only
Classifier: Topic :: Scientific/Engineering :: GIS
Classifier: Topic :: Utilities
Classifier: Typing :: Typed
Requires-Python: <4,>=3.8
License-File: LICENSE.txt
Requires-Dist: gpxpy
Provides-Extra: dev
Requires-Dist: black; extra == "dev"
Requires-Dist: codespell; extra == "dev"
Requires-Dist: flake8; extra == "dev"
Requires-Dist: pep8-naming; extra == "dev"
Requires-Dist: flake8-bugbear; extra == "dev"
Requires-Dist: mypy; extra == "dev"
Requires-Dist: Faker; extra == "dev"
Requires-Dist: importlib-resources; python_version < "3.10" and extra == "dev"
